adc/__init__.py
adc/setup.py
adc/test.py
xtdemo/__init__.py
xtdemo/xt_print.py
xtfixdemo/__init__.py
xtfixdemo/xt_print.py
xtfixdemo-1.0.0.dist-info/METADATA
xtfixdemo-1.0.0.dist-info/WHEEL
xtfixdemo-1.0.0.dist-info/top_level.txt
xtfixdemo-1.0.0.dist-info/RECORD
